dsca/__init__.py
dsca/main.py
dsca-0.1.9.dist-info/METADATA
dsca-0.1.9.dist-info/WHEEL
dsca-0.1.9.dist-info/RECORD
