Metadata-Version: 2.1
Name: dsca
Version: 0.1.9
Summary: Trusting Social's DSCA team API package.
Author: quan-duong-ts
Author-email: quan.duong@trustingsocial.com
Requires-Python: >=3.9,<4.0
Classifier: Programming Language :: Python :: 3
Classifier: Programming Language :: Python :: 3.9
Classifier: Programming Language :: Python :: 3.10
Classifier: Programming Language :: Python :: 3.11
